Metadata-Version: 2.1
Name: redis
Version: 5.3.0
Summary: Python client for Redis database and key-value store
Home-page: https://github.com/redis/redis-py
Author: Redis Inc.
Author-email: oss@redis.com
License: MIT
Project-URL: Documentation, https://redis.readthedocs.io/en/latest/
Project-URL: Changes, https://github.com/redis/redis-py/releases
Project-URL: Code, https://github.com/redis/redis-py
Project-URL: Issue tracker, https://github.com/redis/redis-py/issues
Keywords: Redis,key-value store,database
Platform: UNKNOWN
Classifier: Development Status :: 5 - Production/Stable
Classifier: Environment :: Console
Classifier: Intended Audience :: Developers
Classifier: License :: OSI Approved :: MIT License
Classifier: Operating System :: OS Independent
Classifier: Programming Language :: Python
Classifier: Programming Language :: Python :: 3
Classifier: Programming Language :: Python :: 3 :: Only
Classifier: Programming Language :: Python :: 3.8
Classifier: Programming Language :: Python :: 3.9
Classifier: Programming Language :: Python :: 3.10
Classifier: Programming Language :: Python :: 3.11
Classifier: Programming Language :: Python :: 3.12
Classifier: Programming Language :: Python :: Implementation :: CPython
Classifier: Programming Language :: Python :: Implementation :: PyPy
Requires-Python: >=3.8
Provides-Extra: hiredis
Provides-Extra: ocsp
License-File: LICENSE
